cmg/__init__.py
cmg/cli.py
cmg/generator.py
cmg/schema.py
cmg/templates/cmakelists_txt_j2.py
cmg/templates/identifiable_cpp_j2.py
cmg/templates/identifiable_hpp_j2.py
cmg/templates/index_cpp_j2.py
cmg/templates/index_hpp_j2.py
cmg/templates/klass_cpp_j2.py
cmg/templates/klass_hpp_j2.py
cmg/templates/persistable_hpp_j2.py
cmg/templates/persistence_hpp_j2.py
cmg/templates/test_cpp_j2.py
cmg/validation.py
cmg-1.2.1.dist-info/LICENSE
cmg-1.2.1.dist-info/METADATA
cmg-1.2.1.dist-info/WHEEL
cmg-1.2.1.dist-info/entry_points.txt
cmg-1.2.1.dist-info/RECORD
