Metadata-Version: 2.3
Name: cmg
Version: 1.2.1
Summary: C++11 model generation
Home-page: https://github.com/johndru-astrophysics/cmg
License: MIT
Author: John Dru
Author-email: john@muopia.com
Requires-Python: >=3.11,<3.14
Classifier: License :: OSI Approved :: MIT License
Classifier: Programming Language :: Python :: 3
Classifier: Programming Language :: Python :: 3.11
Classifier: Programming Language :: Python :: 3.12
Classifier: Programming Language :: Python :: 3.13
Requires-Dist: click (>=8.1.8,<9.0.0)
Requires-Dist: jinja2 (>=3.1.4,<4.0.0)
Project-URL: Documentation, https://johndru-astrophysics.github.io/cmg
Project-URL: Repository, https://github.com/johndru-astrophysics/cmg
